gpt_from_scratch/__init__.py
gpt_from_scratch/dataset/__init__.py
gpt_from_scratch/dataset/dataloader.py
gpt_from_scratch/dataset/shardmanager.py
gpt_from_scratch/dataset/tokenizer.py
gpt_from_scratch/dataset/utils.py
gpt_from_scratch/metrics/__init__.py
gpt_from_scratch/metrics/hellaswag.py
gpt_from_scratch/models/__init__.py
gpt_from_scratch/models/_modules.py
gpt_from_scratch/models/gpt.py
gpt_from_scratch/models/utils.py
gpt_from_scratch/trainers/__init__.py
gpt_from_scratch/trainers/trainer.py
gpt_from_scratch-1.1.dist-info/METADATA
gpt_from_scratch-1.1.dist-info/WHEEL
gpt_from_scratch-1.1.dist-info/top_level.txt
gpt_from_scratch-1.1.dist-info/RECORD
