Metadata-Version: 2.1
Name: gpt-from-scratch
Version: 1.1
Summary: Scalable GPT implementation using Distributed Data Parallel for efficient, multi-GPU training of transformer models.
Home-page: https://github.com/MatinKhajavi/GPT-from-scratch
License: MIT
Classifier: Programming Language :: Python :: 3.12
Classifier: Environment :: Console
Classifier: Framework :: Jupyter
Classifier: License :: OSI Approved :: MIT License
Classifier: Natural Language :: English
Classifier: Operating System :: MacOS :: MacOS X
Classifier: Operating System :: Microsoft :: Windows
Classifier: Operating System :: POSIX :: Linux
Requires-Dist: datasets
Requires-Dist: numpy
Requires-Dist: Requests
Requires-Dist: tiktoken >=0.7.0
Requires-Dist: torch
Requires-Dist: tqdm
Requires-Dist: matplotlib
Requires-Dist: seaborn
